{"stage_id": 5000, "start_time": 1638640800, "shift_type": "normal", "end_time": 1638792000, "weapon_list": [3000, 1030, 6000, 240], "rare_weapon": null, "records": {"golden_eggs": {"total": {"id": 1891612, "members": ["2f64b91c4ee5b9a4", "4e217af8576c7364", "759f8285abd07135", "ae570b2064d4b4b6"], "golden_eggs": 179, "power_eggs": 4385, "water_level": null, "event_type": null}, "no_night_event": {"id": 1895018, "members": ["06c67b2444620bf8", "42e37bcfdb386e21", "a0720e1c8cecd9fc", "ff05b28c6138a248"], "golden_eggs": 162, "power_eggs": 3004, "water_level": null, "event_type": null}, "waves": [{"id": 1891588, "members": ["0fc55140cd215f52", "2da02f4acf9dccfe", "408560c9cf5623e5", "9019e949388fd0f4"], "golden_eggs": 61, "power_eggs": 1216, "water_level": "low", "event_type": "-"}, {"id": 1892672, "members": ["06c67b2444620bf8", "290c8ad7568eb45a", "747b37c7b2f790bf", "ae783901c03b1dc6"], "golden_eggs": 58, "power_eggs": 2227, "water_level": "low", "event_type": "cohock-charge"}, {"id": 1895007, "members": ["06c67b2444620bf8", "2190d31444d47ae1", "5db950fcf6763803", "b23d4162b1efb667"], "golden_eggs": 64, "power_eggs": 1238, "water_level": "low", "event_type": "fog"}, {"id": 1892260, "members": ["488696bee66075d1", "ae783901c03b1dc6", "d981afaa24f1febd", "ef41aa181c1d4a72"], "golden_eggs": 54, "power_eggs": 1005, "water_level": "low", "event_type": "the-mothership"}, {"id": 1893519, "members": ["55f850dd60952002", "5db950fcf6763803", "701f07f4f86556c0", "ae570b2064d4b4b6"], "golden_eggs": 63, "power_eggs": 1002, "water_level": "normal", "event_type": "-"}, {"id": 1895220, "members": ["2190d31444d47ae1", "4e217af8576c7364", "ae570b2064d4b4b6", "ef41aa181c1d4a72"], "golden_eggs": 70, "power_eggs": 995, "water_level": "normal", "event_type": "fog"}, {"id": 1894766, "members": ["3e44c8b5d74a5d37", "488696bee66075d1", "8693b36d8d6036c6", "d6d01180fb70375b"], "golden_eggs": 52, "power_eggs": 1041, "water_level": "normal", "event_type": "goldie-seeking"}, {"id": 1893225, "members": ["06c67b2444620bf8", "0fc55140cd215f52", "42e37bcfdb386e21", "ff05b28c6138a248"], "golden_eggs": 63, "power_eggs": 1473, "water_level": "normal", "event_type": "griller"}, {"id": 1893518, "members": ["55f850dd60952002", "701f07f4f86556c0", "ae570b2064d4b4b6", "e8aeb75f0a8c90b5"], "golden_eggs": 48, "power_eggs": 811, "water_level": "normal", "event_type": "the-mothership"}, {"id": 1895077, "members": ["06c67b2444620bf8", "42e37bcfdb386e21", "a0720e1c8cecd9fc", "ff05b28c6138a248"], "golden_eggs": 58, "power_eggs": 2709, "water_level": "normal", "event_type": "rush"}, {"id": 1893526, "members": ["55f850dd60952002", "5db950fcf6763803", "701f07f4f86556c0", "ae570b2064d4b4b6"], "golden_eggs": 64, "power_eggs": 1916, "water_level": "high", "event_type": "-"}, {"id": 1893614, "members": ["06c67b2444620bf8", "2190d31444d47ae1", "5db950fcf6763803", "b23d4162b1efb667"], "golden_eggs": 67, "power_eggs": 1522, "water_level": "high", "event_type": "fog"}, {"id": 1893521, "members": ["55f850dd60952002", "5db950fcf6763803", "701f07f4f86556c0", "ae570b2064d4b4b6"], "golden_eggs": 56, "power_eggs": 1606, "water_level": "high", "event_type": "goldie-seeking"}, {"id": 1893357, "members": ["06c67b2444620bf8", "0fc55140cd215f52", "42e37bcfdb386e21", "ff05b28c6138a248"], "golden_eggs": 75, "power_eggs": 1784, "water_level": "high", "event_type": "griller"}, {"id": 1895257, "members": ["06c67b2444620bf8", "42e37bcfdb386e21", "a0720e1c8cecd9fc", "ff05b28c6138a248"], "golden_eggs": 57, "power_eggs": 1082, "water_level": "high", "event_type": "the-mothership"}, {"id": 1892725, "members": ["06c67b2444620bf8", "290c8ad7568eb45a", "747b37c7b2f790bf", "ae783901c03b1dc6"], "golden_eggs": 67, "power_eggs": 2928, "water_level": "high", "event_type": "rush"}]}, "power_eggs": {"total": {"id": 1893418, "members": ["1525c70d47703782", "29569d6356b7aadb", "2ff80b911efee1f3", "8717c3aa51dcffb2"], "golden_eggs": 100, "power_eggs": 7802, "water_level": null, "event_type": null}, "no_night_event": {"id": 1894762, "members": ["3e44c8b5d74a5d37", "488696bee66075d1", "8693b36d8d6036c6", "fafcec2cc3484fe4"], "golden_eggs": 114, "power_eggs": 4821, "water_level": null, "event_type": null}, "waves": [{"id": 1892796, "members": ["1fdcffd8adf2bd43", "2f3b94839fe0107d", "bbc5c1d51488c609", "fd60398913675234"], "golden_eggs": 34, "power_eggs": 1723, "water_level": "low", "event_type": "-"}, {"id": 1894204, "members": ["21456b9ea4b9de58", "37a2c9631809d35c", "4c2e448503020ad3", "90c31a7caf30eaad"], "golden_eggs": 27, "power_eggs": 3434, "water_level": "low", "event_type": "cohock-charge"}, {"id": 1893954, "members": ["7f6ffde24e34b46b", "a9bba5aac8f7a5c6", "b342441b48497474", "c807b7c5ad3fa690"], "golden_eggs": 48, "power_eggs": 1521, "water_level": "low", "event_type": "fog"}, {"id": 1895759, "members": ["062a8920e09cbfa5", "309b635a14d487df", "7695df0f29e0c51a", "a3e28d539772ac41"], "golden_eggs": 32, "power_eggs": 1110, "water_level": "low", "event_type": "the-mothership"}, {"id": 1892548, "members": ["178332439c5a3b54", "3408013820a01b63", "52d5c2d24314842a", "fc93595c6ab4f07e"], "golden_eggs": 37, "power_eggs": 1344, "water_level": "normal", "event_type": "-"}, {"id": 1893519, "members": ["55f850dd60952002", "5db950fcf6763803", "701f07f4f86556c0", "ae570b2064d4b4b6"], "golden_eggs": 43, "power_eggs": 1182, "water_level": "normal", "event_type": "fog"}, {"id": 1891615, "members": ["2f64b91c4ee5b9a4", "4e217af8576c7364", "759f8285abd07135", "ae570b2064d4b4b6"], "golden_eggs": 49, "power_eggs": 2043, "water_level": "normal", "event_type": "goldie-seeking"}, {"id": 1894326, "members": ["b2da7c8ca0e06fa7", "cde7ed3fa44ad577", "d43cba838ab9f845", "f0f3704107516f20"], "golden_eggs": 55, "power_eggs": 1618, "water_level": "normal", "event_type": "griller"}, {"id": 1895186, "members": ["3e348e006006e28c", "64abf79d9b10f548", "701f07f4f86556c0", "958f82c466599224"], "golden_eggs": 39, "power_eggs": 904, "water_level": "normal", "event_type": "the-mothership"}, {"id": 1895256, "members": ["06c67b2444620bf8", "42e37bcfdb386e21", "a0720e1c8cecd9fc", "ff05b28c6138a248"], "golden_eggs": 49, "power_eggs": 2791, "water_level": "normal", "event_type": "rush"}, {"id": 1895012, "members": ["06c67b2444620bf8", "0c69b182fdc05040", "434f7362b40416cc", "7a61697c55e0ae37"], "golden_eggs": 46, "power_eggs": 2264, "water_level": "high", "event_type": "-"}, {"id": 1893529, "members": ["55f850dd60952002", "701f07f4f86556c0", "ae570b2064d4b4b6", "e8aeb75f0a8c90b5"], "golden_eggs": 66, "power_eggs": 1680, "water_level": "high", "event_type": "fog"}, {"id": 1896113, "members": ["485db8f3e6e16700", "6369cfb3c450de87", "b4a789088b5cebf7", "f36bcc91cacdab46"], "golden_eggs": 34, "power_eggs": 2541, "water_level": "high", "event_type": "goldie-seeking"}, {"id": 1893625, "members": ["0fc55140cd215f52", "1c358b472c8f66c3", "250d09d5cc6c6819", "747b37c7b2f790bf"], "golden_eggs": 62, "power_eggs": 1839, "water_level": "high", "event_type": "griller"}, {"id": 1891393, "members": ["19ec529903aba6ed", "7ad10f1f0cb5ae6b", "7d19645e5d231fc9", "a40245a8a0b8624a"], "golden_eggs": 32, "power_eggs": 1871, "water_level": "high", "event_type": "the-mothership"}, {"id": 1893182, "members": ["23038a91b3db9351", "b77a51eb7d377a39", "f7e8d07c3089eaaa", "fc93595c6ab4f07e"], "golden_eggs": 41, "power_eggs": 3373, "water_level": "high", "event_type": "rush"}]}}}