{"stage_id": 5004, "start_time": 1640995200, "shift_type": "normal", "end_time": 1641146400, "weapon_list": [10, 1000, 40, 2000], "rare_weapon": null, "records": {"golden_eggs": {"total": {"id": 1952452, "members": ["4e217af8576c7364", "857351344f5b5096", "ae570b2064d4b4b6", "d50a82bbc795da65"], "golden_eggs": 208, "power_eggs": 5164, "water_level": null, "event_type": null}, "no_night_event": {"id": 1951961, "members": ["130bc23765f62e0a", "739c14d90f74f3b2", "cde7ed3fa44ad577", "f8cf06eafc5113c2"], "golden_eggs": 175, "power_eggs": 4775, "water_level": null, "event_type": null}, "waves": [{"id": 1950557, "members": ["0fc55140cd215f52", "5db950fcf6763803", "701f07f4f86556c0", "a6698b80745752ab"], "golden_eggs": 66, "power_eggs": 1437, "water_level": "low", "event_type": "-"}, {"id": 1952601, "members": ["290c8ad7568eb45a", "a98290c42048eab1", "b23d4162b1efb667", "d6d01180fb70375b"], "golden_eggs": 60, "power_eggs": 1918, "water_level": "low", "event_type": "cohock-charge"}, {"id": 1952452, "members": ["4e217af8576c7364", "857351344f5b5096", "ae570b2064d4b4b6", "d50a82bbc795da65"], "golden_eggs": 76, "power_eggs": 1401, "water_level": "low", "event_type": "fog"}, {"id": 1952746, "members": ["23038a91b3db9351", "4e217af8576c7364", "857351344f5b5096", "ae570b2064d4b4b6"], "golden_eggs": 56, "power_eggs": 835, "water_level": "low", "event_type": "the-mothership"}, {"id": 1952937, "members": ["1d29600f0a1d64db", "290c8ad7568eb45a", "43141d650dca1e22", "d6d01180fb70375b"], "golden_eggs": 60, "power_eggs": 815, "water_level": "normal", "event_type": "-"}, {"id": 1951543, "members": ["4e217af8576c7364", "5db950fcf6763803", "a6698b80745752ab", "b23d4162b1efb667"], "golden_eggs": 61, "power_eggs": 779, "water_level": "normal", "event_type": "fog"}, {"id": 1948389, "members": ["28e0c8f7df91f431", "2f64b91c4ee5b9a4", "66ffbce054aa5291", "aa346071b3576101"], "golden_eggs": 63, "power_eggs": 1258, "water_level": "normal", "event_type": "goldie-seeking"}, {"id": 1948900, "members": ["28e0c8f7df91f431", "2f64b91c4ee5b9a4", "66ffbce054aa5291", "aa346071b3576101"], "golden_eggs": 55, "power_eggs": 1262, "water_level": "normal", "event_type": "griller"}, {"id": 1950711, "members": ["0fc55140cd215f52", "5db950fcf6763803", "701f07f4f86556c0", "a6698b80745752ab"], "golden_eggs": 58, "power_eggs": 552, "water_level": "normal", "event_type": "the-mothership"}, {"id": 1951468, "members": ["4e217af8576c7364", "5db950fcf6763803", "a6698b80745752ab", "b23d4162b1efb667"], "golden_eggs": 54, "power_eggs": 2171, "water_level": "normal", "event_type": "rush"}, {"id": 1953909, "members": ["2e86f880e0fcdbcb", "788580029fe74552", "ae570b2064d4b4b6", "d50a82bbc795da65"], "golden_eggs": 72, "power_eggs": 1597, "water_level": "high", "event_type": "-"}, {"id": 1948977, "members": ["5db950fcf6763803", "857351344f5b5096", "a6698b80745752ab", "ae570b2064d4b4b6"], "golden_eggs": 78, "power_eggs": 1559, "water_level": "high", "event_type": "fog"}, {"id": 1954813, "members": ["2e86f880e0fcdbcb", "4e217af8576c7364", "701f07f4f86556c0", "ae570b2064d4b4b6"], "golden_eggs": 87, "power_eggs": 1891, "water_level": "high", "event_type": "goldie-seeking"}, {"id": 1952452, "members": ["4e217af8576c7364", "857351344f5b5096", "ae570b2064d4b4b6", "d50a82bbc795da65"], "golden_eggs": 85, "power_eggs": 1871, "water_level": "high", "event_type": "griller"}, {"id": 1953011, "members": ["0fc55140cd215f52", "408560c9cf5623e5", "5db950fcf6763803", "a205f0c9af03ff08"], "golden_eggs": 80, "power_eggs": 856, "water_level": "high", "event_type": "the-mothership"}, {"id": 1954498, "members": ["227e89ca979963a5", "327a067156d989b3", "a0720e1c8cecd9fc", "cba7dafd7394c67f"], "golden_eggs": 66, "power_eggs": 3367, "water_level": "high", "event_type": "rush"}]}, "power_eggs": {"total": {"id": 1949169, "members": ["390e21f636e0dc6b", "5cf213375ccc9105", "88cd6c685029f0c3", "e5483de168532555"], "golden_eggs": 112, "power_eggs": 7169, "water_level": null, "event_type": null}, "no_night_event": {"id": 1953815, "members": ["390e21f636e0dc6b", "4035fc378ab11356", "7d97c68e133d9bdb", "e5483de168532555"], "golden_eggs": 124, "power_eggs": 5110, "water_level": null, "event_type": null}, "waves": [{"id": 1951044, "members": ["22c0295ef7aacaf4", "290c8ad7568eb45a", "a98290c42048eab1", "de3804f076bdec38"], "golden_eggs": 44, "power_eggs": 1614, "water_level": "low", "event_type": "-"}, {"id": 1948683, "members": ["40fa827b5f268dd5", "4ced4f1d9f1d0e7f", "65d1fc6c5f081129", "d8d821aa9752db5f"], "golden_eggs": 21, "power_eggs": 2915, "water_level": "low", "event_type": "cohock-charge"}, {"id": 1952786, "members": ["1d29600f0a1d64db", "290c8ad7568eb45a", "43141d650dca1e22", "d6d01180fb70375b"], "golden_eggs": 74, "power_eggs": 1481, "water_level": "low", "event_type": "fog"}, {"id": 1953783, "members": ["7b0f5dc9af24b385", "afb7051c774ed605", "b993da54fd6a40ca", "e762bc2f9759f1ba"], "golden_eggs": 39, "power_eggs": 1063, "water_level": "low", "event_type": "the-mothership"}, {"id": 1950228, "members": ["1a1e2c97fcf0e08f", "6e9428072a4fb290", "a1ac0bdec2b40251", "b7d9be77340d655b"], "golden_eggs": 28, "power_eggs": 1149, "water_level": "normal", "event_type": "-"}, {"id": 1952740, "members": ["84b71660dc04ef52", "c214b5f3b68b2a24", "d8d821aa9752db5f", "e9fa4f69d4bdc4b4"], "golden_eggs": 30, "power_eggs": 865, "water_level": "normal", "event_type": "fog"}, {"id": 1953959, "members": ["06c67b2444620bf8", "2190d31444d47ae1", "408560c9cf5623e5", "43141d650dca1e22"], "golden_eggs": 35, "power_eggs": 1759, "water_level": "normal", "event_type": "goldie-seeking"}, {"id": 1954733, "members": ["187d9d4f34632446", "3e51d668292e75d4", "4c6e1f5e267c9a7e", "cf8bece8db4121c5"], "golden_eggs": 36, "power_eggs": 1334, "water_level": "normal", "event_type": "griller"}, {"id": 2009982, "members": ["439c5d5f5a0f0e4c", "58d58a4a6564ea90", "639e315f7cbfed80", "90a9d37917d736a4"], "golden_eggs": 44, "power_eggs": 775, "water_level": "normal", "event_type": "the-mothership"}, {"id": 1957067, "members": ["2e86f880e0fcdbcb", "4e217af8576c7364", "701f07f4f86556c0", "ae570b2064d4b4b6"], "golden_eggs": 48, "power_eggs": 2181, "water_level": "normal", "event_type": "rush"}, {"id": 1953726, "members": ["4c1e59670b894021", "958f82c466599224", "c80a20dd8ac9af96", "eff76c88588ba744"], "golden_eggs": 55, "power_eggs": 2236, "water_level": "high", "event_type": "-"}, {"id": 1949358, "members": ["0fc55140cd215f52", "8693b36d8d6036c6", "a6ff7272d54eb552", "dd78430267ee78b7"], "golden_eggs": 44, "power_eggs": 1819, "water_level": "high", "event_type": "fog"}, {"id": 1951386, "members": ["390e21f636e0dc6b", "77201d8628ebbec1", "d040b36b6e7c3a15", "e5483de168532555"], "golden_eggs": 29, "power_eggs": 2892, "water_level": "high", "event_type": "goldie-seeking"}, {"id": 1948422, "members": ["28e0c8f7df91f431", "2f64b91c4ee5b9a4", "66ffbce054aa5291", "aa346071b3576101"], "golden_eggs": 62, "power_eggs": 1960, "water_level": "high", "event_type": "griller"}, {"id": 1952095, "members": ["8ff60a8d62168bf1", "cde7ed3fa44ad577", "d1f23c2c27df69be", "f2d0a1c488666a32"], "golden_eggs": 76, "power_eggs": 1119, "water_level": "high", "event_type": "the-mothership"}, {"id": 1948643, "members": ["28e0c8f7df91f431", "2f64b91c4ee5b9a4", "66ffbce054aa5291", "aa346071b3576101"], "golden_eggs": 56, "power_eggs": 3558, "water_level": "high", "event_type": "rush"}]}}}