{"stage_id": 5001, "start_time": 1650564000, "shift_type": "normal", "end_time": 1650693600, "weapon_list": [300, 4040, 5030, 2010], "rare_weapon": null, "records": {"golden_eggs": {"total": {"id": 2215108, "members": ["5177c3132e37c3ef", "677b270012fa4e51", "79fcaf9284baf9c8", "ab5f8598e58c9b02"], "golden_eggs": 133, "power_eggs": 6615, "water_level": null, "event_type": null}, "no_night_event": {"id": 2215111, "members": ["5177c3132e37c3ef", "677b270012fa4e51", "79fcaf9284baf9c8", "ab5f8598e58c9b02"], "golden_eggs": 127, "power_eggs": 3586, "water_level": null, "event_type": null}, "waves": [{"id": 2215111, "members": ["5177c3132e37c3ef", "677b270012fa4e51", "79fcaf9284baf9c8", "ab5f8598e58c9b02"], "golden_eggs": 46, "power_eggs": 1291, "water_level": "low", "event_type": "-"}, {"id": 2215108, "members": ["5177c3132e37c3ef", "677b270012fa4e51", "79fcaf9284baf9c8", "ab5f8598e58c9b02"], "golden_eggs": 43, "power_eggs": 2685, "water_level": "low", "event_type": "cohock-charge"}, {"id": 2215022, "members": ["4605135a7ac625b3", "54d48f0553cfdf85", "9a4b36508d3eb9e7", "bda919136a68cb74"], "golden_eggs": 48, "power_eggs": 951, "water_level": "low", "event_type": "fog"}, {"id": 2215035, "members": ["36413ef5fe9cf17f", "6e04955dee03f42f", "b233b12395ffccf6", "d7781a6ef98d5dab"], "golden_eggs": 54, "power_eggs": 854, "water_level": "low", "event_type": "the-mothership"}, {"id": 2215108, "members": ["5177c3132e37c3ef", "677b270012fa4e51", "79fcaf9284baf9c8", "ab5f8598e58c9b02"], "golden_eggs": 47, "power_eggs": 825, "water_level": "normal", "event_type": "-"}, {"id": 2215216, "members": ["23c2f1e7af0e339f", "7d744ae9f61a6f20", "a017c5962fe9cb64", "abe2ffb11ec16956"], "golden_eggs": 37, "power_eggs": 554, "water_level": "normal", "event_type": "fog"}, {"id": 2214975, "members": ["346bc5d9f354e77b", "6da235ab2aa2ab12", "bda919136a68cb74", "eacda6537a9b2429"], "golden_eggs": 45, "power_eggs": 954, "water_level": "normal", "event_type": "goldie-seeking"}, {"id": 2215123, "members": ["26dd1babf7072f95", "4605135a7ac625b3", "bda919136a68cb74", "f7cd63c2e7876bc4"], "golden_eggs": 34, "power_eggs": 911, "water_level": "normal", "event_type": "griller"}, {"id": 2215027, "members": ["4234bddfce4fc855", "462d7981fbf29275", "acf1590bed791d99", "f1af236c86e228fd"], "golden_eggs": 40, "power_eggs": 613, "water_level": "normal", "event_type": "the-mothership"}, {"id": 2215019, "members": ["5177c3132e37c3ef", "677b270012fa4e51", "79fcaf9284baf9c8", "ab5f8598e58c9b02"], "golden_eggs": 29, "power_eggs": 2035, "water_level": "normal", "event_type": "rush"}, {"id": 2215131, "members": ["2f64b91c4ee5b9a4", "4605135a7ac625b3", "bda919136a68cb74", "f7cd63c2e7876bc4"], "golden_eggs": 39, "power_eggs": 1144, "water_level": "high", "event_type": "-"}, {"id": 2215117, "members": ["4605135a7ac625b3", "881cb20ff07ac887", "bda919136a68cb74", "f7cd63c2e7876bc4"], "golden_eggs": 37, "power_eggs": 1064, "water_level": "high", "event_type": "fog"}, {"id": 2215219, "members": ["6e7e94d39f2ab54d", "7d744ae9f61a6f20", "a752386842d300c2", "d2c76c99aa257356"], "golden_eggs": 39, "power_eggs": 1232, "water_level": "high", "event_type": "goldie-seeking"}, {"id": 2215026, "members": ["5177c3132e37c3ef", "677b270012fa4e51", "79fcaf9284baf9c8", "ab5f8598e58c9b02"], "golden_eggs": 33, "power_eggs": 1171, "water_level": "high", "event_type": "griller"}, {"id": 2215220, "members": ["55a74b4280e6fe27", "6fbf9b027a72dcd1", "7d744ae9f61a6f20", "d2c76c99aa257356"], "golden_eggs": 34, "power_eggs": 887, "water_level": "high", "event_type": "the-mothership"}, {"id": 2215108, "members": ["5177c3132e37c3ef", "677b270012fa4e51", "79fcaf9284baf9c8", "ab5f8598e58c9b02"], "golden_eggs": 43, "power_eggs": 3105, "water_level": "high", "event_type": "rush"}]}, "power_eggs": {"total": {"id": 2215108, "members": ["5177c3132e37c3ef", "677b270012fa4e51", "79fcaf9284baf9c8", "ab5f8598e58c9b02"], "golden_eggs": 133, "power_eggs": 6615, "water_level": null, "event_type": null}, "no_night_event": {"id": 2215111, "members": ["5177c3132e37c3ef", "677b270012fa4e51", "79fcaf9284baf9c8", "ab5f8598e58c9b02"], "golden_eggs": 127, "power_eggs": 3586, "water_level": null, "event_type": null}, "waves": [{"id": 2215034, "members": ["36413ef5fe9cf17f", "40413f47016d33e2", "98f3aa8cfc8088f9", "a4bc9d6c1a2733e9"], "golden_eggs": 33, "power_eggs": 1435, "water_level": "low", "event_type": "-"}, {"id": 2215099, "members": ["4d6f0a2045b1aebe", "7ab5d5e1f6148be4", "a111710797f76e20", "a8ed4bac1df17902"], "golden_eggs": 23, "power_eggs": 2752, "water_level": "low", "event_type": "cohock-charge"}, {"id": 2215031, "members": ["169ceb9297eb9d58", "311271dfa5b7a5b8", "36413ef5fe9cf17f", "522ccd8f71323d5f"], "golden_eggs": 29, "power_eggs": 1036, "water_level": "low", "event_type": "fog"}, {"id": 2214962, "members": ["6fc7ec4ae201c81c", "94d8e222dde1d6fc", "c6802004f32e6c8e", "dfbadd120e5cba4d"], "golden_eggs": 26, "power_eggs": 914, "water_level": "low", "event_type": "the-mothership"}, {"id": 2215109, "members": ["128a4a5d10af0d02", "4605135a7ac625b3", "bda919136a68cb74", "f7cd63c2e7876bc4"], "golden_eggs": 26, "power_eggs": 914, "water_level": "normal", "event_type": "-"}, {"id": 2214884, "members": ["0ab6111c707048a0", "784fa54ea3147463", "d0c4220829bcd7b1", "f2d0f5010444e4d1"], "golden_eggs": 32, "power_eggs": 746, "water_level": "normal", "event_type": "fog"}, {"id": 2215169, "members": ["677b270012fa4e51", "ab5f8598e58c9b02", "b486255fcba49c11", "f00f656b49f9c802"], "golden_eggs": 37, "power_eggs": 1147, "water_level": "normal", "event_type": "goldie-seeking"}, {"id": 2215214, "members": ["6100add221d35d7e", "7d744ae9f61a6f20", "c73967441a48a9f5", "f442a32ad240bc75"], "golden_eggs": 23, "power_eggs": 941, "water_level": "normal", "event_type": "griller"}, {"id": 2215034, "members": ["36413ef5fe9cf17f", "40413f47016d33e2", "98f3aa8cfc8088f9", "a4bc9d6c1a2733e9"], "golden_eggs": 32, "power_eggs": 669, "water_level": "normal", "event_type": "the-mothership"}, {"id": 2215035, "members": ["36413ef5fe9cf17f", "6e04955dee03f42f", "b233b12395ffccf6", "d7781a6ef98d5dab"], "golden_eggs": 24, "power_eggs": 2131, "water_level": "normal", "event_type": "rush"}, {"id": 2215117, "members": ["4605135a7ac625b3", "881cb20ff07ac887", "bda919136a68cb74", "f7cd63c2e7876bc4"], "golden_eggs": 28, "power_eggs": 1443, "water_level": "high", "event_type": "-"}, {"id": 2214994, "members": ["5177c3132e37c3ef", "79fcaf9284baf9c8", "95d5d9ce52e3e9dc", "9d74f14b4a14afef"], "golden_eggs": 20, "power_eggs": 1138, "water_level": "high", "event_type": "fog"}, {"id": 2214971, "members": ["91d38a0159703d90", "bda919136a68cb74", "c281e0146bf6a8ff", "ff3939c7b3819747"], "golden_eggs": 23, "power_eggs": 1359, "water_level": "high", "event_type": "goldie-seeking"}, {"id": 2215011, "members": ["49ada8b3a2e7d31d", "5177c3132e37c3ef", "79fcaf9284baf9c8", "ab5f8598e58c9b02"], "golden_eggs": 30, "power_eggs": 1278, "water_level": "high", "event_type": "griller"}, {"id": 2215238, "members": ["42b8eb952f5b68d9", "609e9a0136d54772", "bb71571eacb80d62", "e592b3e7fcb4fc39"], "golden_eggs": 32, "power_eggs": 985, "water_level": "high", "event_type": "the-mothership"}, {"id": 2215108, "members": ["5177c3132e37c3ef", "677b270012fa4e51", "79fcaf9284baf9c8", "ab5f8598e58c9b02"], "golden_eggs": 43, "power_eggs": 3105, "water_level": "high", "event_type": "rush"}]}}}